stashcookie/cookie.py
stashcookie-0.1.7.dist-info/METADATA
stashcookie-0.1.7.dist-info/WHEEL
stashcookie-0.1.7.dist-info/entry_points.txt
stashcookie-0.1.7.dist-info/top_level.txt
stashcookie-0.1.7.dist-info/RECORD
