Metadata-Version: 2.4
Name: stashcookie
Version: 0.1.7
Summary: store big files to amazon glacier
Author-email: Your Name <abram.handler@gmail.com>
